[
  {
    "name": "Pablo (Bluesman)",
    "slug": "pablo",
    "description": "Can play the blues harp to make four levels of noise",
    "avatar": 308,
    "life": 3,
    "actions": 3,
    "inventory": 4,
    "defense": 0,
    "movement": 1,
    "noise": 4
  },
  {
    "name": "Miguel (Deep pockets)",
    "slug": "miguel",
    "description": "Carry more things. Five inventory slots",
    "avatar": 307,
    "life": 3,
    "actions": 3,
    "inventory": 5,
    "defense": 0,
    "movement": 1,
    "noise": 2
  },
  {
    "name": "Laura (Healthy)",
    "slug": "laura",
    "description": "Have four life points",
    "avatar": 306,
    "life": 4,
    "actions": 3,
    "inventory": 4,
    "defense": 0,
    "movement": 1,
    "noise": 2
  },
  {
    "name": "Yami (Though gal)",
    "slug": "yami",
    "description": "Receives one less damage by attack, but only has two life points",
    "avatar": 310,
    "life": 2,
    "actions": 3,
    "inventory": 4,
    "defense": 1,
    "movement": 1,
    "noise": 2
  },
  {
    "name": "Xenia (Rollergirl)",
    "slug": "xenia",
    "description": "She has a pair of rollerblades, so can roll two squares when moves",
    "avatar": 309,
    "life": 3,
    "actions": 3,
    "inventory": 4,
    "defense": 0,
    "movement": 2,
    "noise": 2
  },
  {
    "name": "Alex (Actionman)",
    "slug": "alex",
    "description": "Combat veteran, has four actions, but only one life points",
    "avatar": 305,
    "life": 1,
    "actions": 4,
    "inventory": 4,
    "defense": 1,
    "movement": 1,
    "noise": 2
  },
  {
    "name": "Paul  (Company CEO)",
    "slug": "paul",
    "description": "Great time management skills, has four actions, but only one life points",
    "avatar": 316,
    "life": 1,
    "actions": 4,
    "inventory": 4,
    "defense": 1,
    "movement": 1,
    "noise": 2
  },
  {
    "name": "Antonio  (Hawaiian musician)",
    "slug": "antonio",
    "description": "Can play the ukelele harp to make four levels of noise",
    "avatar": 312,
    "life": 3,
    "actions": 3,
    "inventory": 4,
    "defense": 0,
    "movement": 1,
    "noise": 4
  },
  {
    "name": "Ivan  (Ninja)",
    "slug": "ivan",
    "description": "Can dodge one damage point by attack, but only has two life points",
    "avatar": 314,
    "life": 2,
    "actions": 3,
    "inventory": 4,
    "defense": 1,
    "movement": 1,
    "noise": 2
  },
  {
    "name": "Alejandro  (Crossfitter)",
    "slug": "alejandro",
    "description": "Phisical prowess! He has four life points",
    "avatar": 311,
    "life": 4,
    "actions": 3,
    "inventory": 4,
    "defense": 0,
    "movement": 1,
    "noise": 2
  },
  {
    "name": "Jesus  (Strong man)",
    "slug": "jesus",
    "description": "He is so strong that can carry 5 items",
    "avatar": 315,
    "life": 3,
    "actions": 3,
    "inventory": 5,
    "defense": 0,
    "movement": 1,
    "noise": 2
  },
  {
    "name": "David  (Fast)",
    "slug": "david",
    "description": "He is fast! Moves two squares every time",
    "avatar": 313,
    "life": 3,
    "actions": 3,
    "inventory": 4,
    "defense": 0,
    "movement": 2,
    "noise": 2
  }
]
